LICENSE
MANIFEST.in
README.rst
setup.py
django_tornado_websockets.egg-info/PKG-INFO
django_tornado_websockets.egg-info/SOURCES.txt
django_tornado_websockets.egg-info/dependency_links.txt
django_tornado_websockets.egg-info/requires.txt
django_tornado_websockets.egg-info/top_level.txt
docs/Makefile
docs/make.bat
docs/build/doctrees/api.doctree
docs/build/doctrees/django_integration_configuration.doctree
docs/build/doctrees/environment.pickle
docs/build/doctrees/index.doctree
docs/build/doctrees/installation.doctree
docs/build/doctrees/modules.doctree
docs/build/doctrees/usage.doctree
docs/build/html/.buildinfo
docs/build/html/api.html
docs/build/html/django_integration_configuration.html
docs/build/html/genindex.html
docs/build/html/index.html
docs/build/html/installation.html
docs/build/html/modules.html
docs/build/html/objects.inv
docs/build/html/py-modindex.html
docs/build/html/search.html
docs/build/html/searchindex.js
docs/build/html/usage.html
docs/build/html/_images/django-tornado-websockets_functionning.svg
docs/build/html/_modules/index.html
docs/build/html/_modules/tornado_websockets/exceptions.html
docs/build/html/_modules/tornado_websockets/tornadowrapper.html
docs/build/html/_modules/tornado_websockets/websocket.html
docs/build/html/_modules/tornado_websockets/websockethandler.html
docs/build/html/_modules/tornado_websockets/modules/module.html
docs/build/html/_modules/tornado_websockets/modules/progress_bar.html
docs/build/html/_modules/tornado_websockets/modules/progressbar.html
docs/build/html/_sources/api.txt
docs/build/html/_sources/django_integration_configuration.txt
docs/build/html/_sources/index.txt
docs/build/html/_sources/installation.txt
docs/build/html/_sources/modules.txt
docs/build/html/_sources/usage.txt
docs/build/html/_static/ajax-loader.gif
docs/build/html/_static/basic.css
docs/build/html/_static/comment-bright.png
docs/build/html/_static/comment-close.png
docs/build/html/_static/comment.png
docs/build/html/_static/doctools.js
docs/build/html/_static/down-pressed.png
docs/build/html/_static/down.png
docs/build/html/_static/file.png
docs/build/html/_static/jquery-1.11.1.js
docs/build/html/_static/jquery.js
docs/build/html/_static/minus.png
docs/build/html/_static/plus.png
